# **FooCorporation**

## **General Information**
Magic `0xCAFEBABE`  
Minor version `0`  
Major version `46`[`1.2`]  
Constant Pool Count `100`  
Access Flags `0x0021` [` ACC_SUPER ACC_PUBLIC `]  
This Class `34` `<FooCorporation>`  
Super Class `38` `<java/lang/Object>`  
Interfaces Count `0`  
Fields Count `2`  
Methods Count `3`  
Attributes Count `1`

## **Constant Pool**  

<details> <summary>Show more</summary> <hr>

### [1] *CONSTANT_Methodref_info*
- Class Index `38`
- Name And Type Index `53`

### [2] *CONSTANT_Fieldref_info*
- Class Index `34`
- Class Name `<FooCorporation>`
- Name And Type Index `54`
- Name And Type `<salarioTotal:F>`

### [3] *CONSTANT_Class_info*
- Name Index `55`
- Class Name `<Empregado>`

### [4] *CONSTANT_Fieldref_info*
- Class Index `34`
- Class Name `<FooCorporation>`
- Name And Type Index `56`
- Name And Type `<empregados:[LEmpregado;>`

### [5] *CONSTANT_Class_info*
- Name Index `57`
- Class Name `<Gerente>`

### [6] *CONSTANT_String_info*
- String Index `58`
- String `<Joao>`

### [7] *CONSTANT_String_info*
- String Index `59`
- String `<Silva>`

### [8] *CONSTANT_Float_info*
- Bytes `0x42f00000`
- Float `120`

### [9] *CONSTANT_Methodref_info*
- Class Index `5`
- Name And Type Index `60`

### [10] *CONSTANT_String_info*
- String Index `61`
- String `<Melissa>`

### [11] *CONSTANT_String_info*
- String Index `62`
- String `<Oliveira>`

### [12] *CONSTANT_Float_info*
- Bytes `0x437f8000`
- Float `255.5`

### [13] *CONSTANT_Class_info*
- Name Index `63`
- Class Name `<Engenheiro>`

### [14] *CONSTANT_String_info*
- String Index `64`
- String `<Edson>`

### [15] *CONSTANT_String_info*
- String Index `65`
- String `<Pereira>`

### [16] *CONSTANT_Float_info*
- Bytes `0x435c0000`
- Float `220`

### [17] *CONSTANT_Methodref_info*
- Class Index `13`
- Name And Type Index `60`

### [18] *CONSTANT_String_info*
- String Index `66`
- String `<Felipe>`

### [19] *CONSTANT_String_info*
- String Index `67`
- String `<Brito>`

### [20] *CONSTANT_Float_info*
- Bytes `0x42f90000`
- Float `124.5`

### [21] *CONSTANT_String_info*
- String Index `68`
- String `<Adam>`

### [22] *CONSTANT_Float_info*
- Bytes `0x43780000`
- Float `248`

### [23] *CONSTANT_String_info*
- String Index `69`
- String `<Sofia>`

### [24] *CONSTANT_String_info*
- String Index `70`
- String `<Albuquerque>`

### [25] *CONSTANT_Float_info*
- Bytes `0x43a00000`
- Float `320`

### [26] *CONSTANT_Fieldref_info*
- Class Index `71`
- Class Name `<java/lang/System>`
- Name And Type Index `72`
- Name And Type `<out:Ljava/io/PrintStream;>`

### [27] *CONSTANT_Fieldref_info*
- Class Index `13`
- Class Name `<Engenheiro>`
- Name And Type Index `73`
- Name And Type `<baseSalarial:F>`

### [28] *CONSTANT_Methodref_info*
- Class Index `74`
- Name And Type Index `75`

### [29] *CONSTANT_Fieldref_info*
- Class Index `13`
- Class Name `<Engenheiro>`
- Name And Type Index `76`
- Name And Type `<nome:Ljava/lang/String;>`

### [30] *CONSTANT_Methodref_info*
- Class Index `74`
- Name And Type Index `77`

### [31] *CONSTANT_Methodref_info*
- Class Index `5`
- Name And Type Index `78`

### [32] *CONSTANT_Methodref_info*
- Class Index `13`
- Name And Type Index `79`

### [33] *CONSTANT_Methodref_info*
- Class Index `3`
- Name And Type Index `80`

### [34] *CONSTANT_Class_info*
- Name Index `81`
- Class Name `<FooCorporation>`

### [35] *CONSTANT_Methodref_info*
- Class Index `34`
- Name And Type Index `53`

### [36] *CONSTANT_String_info*
- String Index `82`
- String `<O salario calculado foi de:>`

### [37] *CONSTANT_Methodref_info*
- Class Index `34`
- Name And Type Index `83`

### [38] *CONSTANT_Class_info*
- Name Index `84`
- Class Name `<java/lang/Object>`

### [39] *CONSTANT_Utf8_info*
- Length `12`
- Bytes [ `salarioTotal`]

### [40] *CONSTANT_Utf8_info*
- Length `1`
- Bytes [ `F`]

### [41] *CONSTANT_Utf8_info*
- Length `10`
- Bytes [ `empregados`]

### [42] *CONSTANT_Utf8_info*
- Length `12`
- Bytes [ `[LEmpregado;`]

### [43] *CONSTANT_Utf8_info*
- Length `6`
- Bytes [ `<init>`]

### [44] *CONSTANT_Utf8_info*
- Length `3`
- Bytes [ `()V`]

### [45] *CONSTANT_Utf8_info*
- Length `4`
- Bytes [ `Code`]

### [46] *CONSTANT_Utf8_info*
- Length `15`
- Bytes [ `LineNumberTable`]

### [47] *CONSTANT_Utf8_info*
- Length `10`
- Bytes [ `getSalario`]

### [48] *CONSTANT_Utf8_info*
- Length `3`
- Bytes [ `()F`]

### [49] *CONSTANT_Utf8_info*
- Length `4`
- Bytes [ `main`]

### [50] *CONSTANT_Utf8_info*
- Length `22`
- Bytes [ `([Ljava/lang/String;)V`]

### [51] *CONSTANT_Utf8_info*
- Length `10`
- Bytes [ `SourceFile`]

### [52] *CONSTANT_Utf8_info*
- Length `19`
- Bytes [ `FooCorporation.java`]

### [53] *CONSTANT_NameAndType_info*
- Name Index `43`
- Descriptor Index `44`

### [54] *CONSTANT_NameAndType_info*
- Name Index `39`
- Descriptor Index `40`

### [55] *CONSTANT_Utf8_info*
- Length `9`
- Bytes [ `Empregado`]

### [56] *CONSTANT_NameAndType_info*
- Name Index `41`
- Descriptor Index `42`

### [57] *CONSTANT_Utf8_info*
- Length `7`
- Bytes [ `Gerente`]

### [58] *CONSTANT_Utf8_info*
- Length `4`
- Bytes [ `Joao`]

### [59] *CONSTANT_Utf8_info*
- Length `5`
- Bytes [ `Silva`]

### [60] *CONSTANT_NameAndType_info*
- Name Index `43`
- Descriptor Index `85`

### [61] *CONSTANT_Utf8_info*
- Length `7`
- Bytes [ `Melissa`]

### [62] *CONSTANT_Utf8_info*
- Length `8`
- Bytes [ `Oliveira`]

### [63] *CONSTANT_Utf8_info*
- Length `10`
- Bytes [ `Engenheiro`]

### [64] *CONSTANT_Utf8_info*
- Length `5`
- Bytes [ `Edson`]

### [65] *CONSTANT_Utf8_info*
- Length `7`
- Bytes [ `Pereira`]

### [66] *CONSTANT_Utf8_info*
- Length `6`
- Bytes [ `Felipe`]

### [67] *CONSTANT_Utf8_info*
- Length `5`
- Bytes [ `Brito`]

### [68] *CONSTANT_Utf8_info*
- Length `4`
- Bytes [ `Adam`]

### [69] *CONSTANT_Utf8_info*
- Length `5`
- Bytes [ `Sofia`]

### [70] *CONSTANT_Utf8_info*
- Length `11`
- Bytes [ `Albuquerque`]

### [71] *CONSTANT_Class_info*
- Name Index `86`
- Class Name `<java/lang/System>`

### [72] *CONSTANT_NameAndType_info*
- Name Index `87`
- Descriptor Index `88`

### [73] *CONSTANT_NameAndType_info*
- Name Index `89`
- Descriptor Index `40`

### [74] *CONSTANT_Class_info*
- Name Index `90`
- Class Name `<java/io/PrintStream>`

### [75] *CONSTANT_NameAndType_info*
- Name Index `91`
- Descriptor Index `92`

### [76] *CONSTANT_NameAndType_info*
- Name Index `93`
- Descriptor Index `94`

### [77] *CONSTANT_NameAndType_info*
- Name Index `91`
- Descriptor Index `95`

### [78] *CONSTANT_NameAndType_info*
- Name Index `96`
- Descriptor Index `97`

### [79] *CONSTANT_NameAndType_info*
- Name Index `98`
- Descriptor Index `97`

### [80] *CONSTANT_NameAndType_info*
- Name Index `99`
- Descriptor Index `48`

### [81] *CONSTANT_Utf8_info*
- Length `14`
- Bytes [ `FooCorporation`]

### [82] *CONSTANT_Utf8_info*
- Length `27`
- Bytes [ `O salario calculado foi de:`]

### [83] *CONSTANT_NameAndType_info*
- Name Index `47`
- Descriptor Index `48`

### [84] *CONSTANT_Utf8_info*
- Length `16`
- Bytes [ `java/lang/Object`]

### [85] *CONSTANT_Utf8_info*
- Length `42`
- Bytes [ `(Ljava/lang/String;Ljava/lang/String;FII)V`]

### [86] *CONSTANT_Utf8_info*
- Length `16`
- Bytes [ `java/lang/System`]

### [87] *CONSTANT_Utf8_info*
- Length `3`
- Bytes [ `out`]

### [88] *CONSTANT_Utf8_info*
- Length `21`
- Bytes [ `Ljava/io/PrintStream;`]

### [89] *CONSTANT_Utf8_info*
- Length `12`
- Bytes [ `baseSalarial`]

### [90] *CONSTANT_Utf8_info*
- Length `19`
- Bytes [ `java/io/PrintStream`]

### [91] *CONSTANT_Utf8_info*
- Length `7`
- Bytes [ `println`]

### [92] *CONSTANT_Utf8_info*
- Length `4`
- Bytes [ `(F)V`]

### [93] *CONSTANT_Utf8_info*
- Length `4`
- Bytes [ `nome`]

### [94] *CONSTANT_Utf8_info*
- Length `18`
- Bytes [ `Ljava/lang/String;`]

### [95] *CONSTANT_Utf8_info*
- Length `21`
- Bytes [ `(Ljava/lang/String;)V`]

### [96] *CONSTANT_Utf8_info*
- Length `13`
- Bytes [ `addHorasGolfe`]

### [97] *CONSTANT_Utf8_info*
- Length `4`
- Bytes [ `(I)V`]

### [98] *CONSTANT_Utf8_info*
- Length `15`
- Bytes [ `horasTrafegadas`]

### [99] *CONSTANT_Utf8_info*
- Length `16`
- Bytes [ `pagamentoSemanal`]

</details> <br>

## **Interfaces**

<details> <summary>Show more</summary> <hr>

</details><br>

## **Fields**

<details> <summary>Show more</summary> <hr>

### [0] `salarioTotal`
- Fields Access Flags `0x0002`
[` ACC_PRIVATE `]
- Name Index `39` `<salarioTotal>`
- Descriptor Index `40` `<F>`
- Attribute Count `0`
<details><summary>Show attributes</summary>


</details><br>

### [1] `empregados`
- Fields Access Flags `0x0002`
[` ACC_PRIVATE `]
- Name Index `41` `<empregados>`
- Descriptor Index `42` `<[LEmpregado;>`
- Attribute Count `0`
<details><summary>Show attributes</summary>


</details><br>

</details><br>

## **Methods**
<details> <summary>Show more</summary> <hr>

### [0] `<init>` 
- Methods Access Flags `0x1` [` ACC_PUBLIC `]
- Name Index `43` `<<init>>`
- Descriptor Index `44` `<()V>`
- Attribute Count `1`
<details><summary>Show attributes</summary>

### [0] Code
- Generic info 
  - Attribute name index`45` `<Code>`
  - Attribute length `422`

- Specific info
  - Maximum stack size `7`
  - Maximum local variables `8`
  - Code length `286`
- Bytecode
```
0 aload_0
1 invokespecial #1 <java/lang/Object.<init> : ()V>  
4 aload_0
5 fconst_0
6 putfield #2 <FooCorporation.salarioTotal : F>  
9 aload_0
10 bipush 6
12 anewarray #3 <Invalid tag>  
15 putfield #4 <FooCorporation.empregados : [LEmpregado;>  
18 new #5 <Invalid tag>  
21 dup
22 ldc #6 <Joao>  
24 ldc #7 <Silva>  
26 ldc #8 <120.000000>  
28 bipush 45
30 iconst_1
31 invokespecial #9 <Gerente.<init> : (Ljava/lang/String;Ljava/lang/String;FII)V>  
34 astore_1
35 new #5 <Invalid tag>  
38 dup
39 ldc #10 <Melissa>  
41 ldc #11 <Oliveira>  
43 ldc #12 <255.500000>  
45 bipush 55
47 iconst_2
48 invokespecial #9 <Gerente.<init> : (Ljava/lang/String;Ljava/lang/String;FII)V>  
51 astore_2
52 new #13 <Invalid tag>  
55 dup
56 ldc #14 <Edson>  
58 ldc #15 <Pereira>  
60 ldc #16 <220.000000>  
62 bipush 70
64 iconst_3
65 invokespecial #17 <Engenheiro.<init> : (Ljava/lang/String;Ljava/lang/String;FII)V>  
68 astore_3
69 new #13 <Invalid tag>  
72 dup
73 ldc #18 <Felipe>  
75 ldc #19 <Brito>  
77 ldc #20 <124.500000>  
79 bipush 42
81 iconst_4
82 invokespecial #17 <Engenheiro.<init> : (Ljava/lang/String;Ljava/lang/String;FII)V>  
85 astore #4
87 new #13 <Invalid tag>  
90 dup
91 ldc #21 <Adam>  
93 ldc #7 <Silva>  
95 ldc #22 <248.000000>  
97 bipush 38
99 iconst_5
100 invokespecial #17 <Engenheiro.<init> : (Ljava/lang/String;Ljava/lang/String;FII)V>  
103 astore #5
105 new #13 <Invalid tag>  
108 dup
109 ldc #23 <Sofia>  
111 ldc #24 <Albuquerque>  
113 ldc #25 <320.000000>  
115 bipush 44
117 bipush 6
119 invokespecial #17 <Engenheiro.<init> : (Ljava/lang/String;Ljava/lang/String;FII)V>  
122 astore #6
124 getstatic #26 <java/lang/System.out : Ljava/io/PrintStream;>  
127 aload #6 <Joao>  
129 getfield #27 <Engenheiro.baseSalarial : F>  
132 invokevirtual #28 <java/io/PrintStream.println : (F)V>  
135 getstatic #26 <java/lang/System.out : Ljava/io/PrintStream;>  
138 aload #5 <Invalid tag>  
140 getfield #27 <Engenheiro.baseSalarial : F>  
143 invokevirtual #28 <java/io/PrintStream.println : (F)V>  
146 getstatic #26 <java/lang/System.out : Ljava/io/PrintStream;>  
149 aload #6 <Joao>  
151 getfield #29 <Engenheiro.nome : Ljava/lang/String;>  
154 invokevirtual #30 <java/io/PrintStream.println : (Ljava/lang/String;)V>  
157 getstatic #26 <java/lang/System.out : Ljava/io/PrintStream;>  
160 aload #5 <Invalid tag>  
162 getfield #29 <Engenheiro.nome : Ljava/lang/String;>  
165 invokevirtual #30 <java/io/PrintStream.println : (Ljava/lang/String;)V>  
168 aload_1
169 bipush 10
171 invokevirtual #31 <Gerente.addHorasGolfe : (I)V>  
174 aload_2
175 iconst_5
176 invokevirtual #31 <Gerente.addHorasGolfe : (I)V>  
179 aload_3
180 bipush 8
182 invokevirtual #32 <Engenheiro.horasTrafegadas : (I)V>  
185 aload #4 <FooCorporation.empregados : [LEmpregado;>  
187 bipush 12
189 invokevirtual #32 <Engenheiro.horasTrafegadas : (I)V>  
192 aload #5 <Invalid tag>  
194 iconst_5
195 invokevirtual #32 <Engenheiro.horasTrafegadas : (I)V>  
198 aload #6 <Joao>  
200 bipush 7
202 invokevirtual #32 <Engenheiro.horasTrafegadas : (I)V>  
205 aload_0
206 getfield #4 <FooCorporation.empregados : [LEmpregado;>  
209 iconst_0
210 aload_1
211 aastore
212 aload_0
213 getfield #4 <FooCorporation.empregados : [LEmpregado;>  
216 iconst_1
217 aload_2
218 aastore
219 aload_0
220 getfield #4 <FooCorporation.empregados : [LEmpregado;>  
223 iconst_2
224 aload_3
225 aastore
226 aload_0
227 getfield #4 <FooCorporation.empregados : [LEmpregado;>  
230 iconst_3
231 aload #4 <FooCorporation.empregados : [LEmpregado;>  
233 aastore
234 aload_0
235 getfield #4 <FooCorporation.empregados : [LEmpregado;>  
238 iconst_4
239 aload #5 <Invalid tag>  
241 aastore
242 aload_0
243 getfield #4 <FooCorporation.empregados : [LEmpregado;>  
246 iconst_5
247 aload #6 <Joao>  
249 aastore
250 iconst_0
251 istore #7
253 iload #7
255 bipush 6
257 if_icmpge 28
260 aload_0
261 dup
262 getfield #2 <FooCorporation.salarioTotal : F>  
265 aload_0
266 getfield #4 <FooCorporation.empregados : [LEmpregado;>  
269 iload #7
271 aaload
272 invokevirtual #33 <Empregado.pagamentoSemanal : ()F>  
275 fadd
276 putfield #2 <FooCorporation.salarioTotal : F>  
279 iinc #7 <1>  
282 goto 65507
285 return
```
### [0] LineNumberTable
- Generic info 
  - Attribute name index`46` `<LineNumberTable>`
  - Attribute length `118`

- Specific info
  - Line number table length `29`  

| Number | Start PC | Line Number |  
|--------|----------|-------------|  
|       0|         0|            5|  
|       1|         4|            3|  
|       2|         9|            4|  
|       3|        18|            6|  
|       4|        35|            7|  
|       5|        52|            8|  
|       6|        69|            9|  
|       7|        87|           10|  
|       8|       105|           11|  
|       9|       124|           13|  
|      10|       135|           14|  
|      11|       146|           15|  
|      12|       157|           16|  
|      13|       168|           17|  
|      14|       174|           18|  
|      15|       179|           19|  
|      16|       185|           20|  
|      17|       192|           21|  
|      18|       198|           22|  
|      19|       205|           23|  
|      20|       212|           24|  
|      21|       219|           25|  
|      22|       226|           26|  
|      23|       234|           27|  
|      24|       242|           28|  
|      25|       250|           29|  
|      26|       260|           30|  
|      27|       279|           29|  
|      28|       285|           32|  


</details><br>

### [1] `getSalario` 
- Methods Access Flags `0x1` [` ACC_PUBLIC `]
- Name Index `47` `<getSalario>`
- Descriptor Index `48` `<()F>`
- Attribute Count `1`
<details><summary>Show attributes</summary>

### [0] Code
- Generic info 
  - Attribute name index`45` `<Code>`
  - Attribute length `29`

- Specific info
  - Maximum stack size `1`
  - Maximum local variables `1`
  - Code length `5`
- Bytecode
```
0 aload_0
1 getfield #2 <FooCorporation.salarioTotal : F>  
4 freturn
```
### [0] LineNumberTable
- Generic info 
  - Attribute name index`46` `<LineNumberTable>`
  - Attribute length `6`

- Specific info
  - Line number table length `1`  

| Number | Start PC | Line Number |  
|--------|----------|-------------|  
|       0|         0|           35|  


</details><br>

### [2] `main` 
- Methods Access Flags `0x9` [` `]
- Name Index `49` `<main>`
- Descriptor Index `50` `<([Ljava/lang/String;)V>`
- Attribute Count `1`
<details><summary>Show attributes</summary>

### [0] Code
- Generic info 
  - Attribute name index`45` `<Code>`
  - Attribute length `63`

- Specific info
  - Maximum stack size `2`
  - Maximum local variables `2`
  - Code length `27`
- Bytecode
```
0 new #34 <Invalid tag>  
3 dup
4 invokespecial #35 <FooCorporation.<init> : ()V>  
7 astore_1
8 getstatic #26 <java/lang/System.out : Ljava/io/PrintStream;>  
11 ldc #36 <O salario calculado foi de:>  
13 invokevirtual #30 <java/io/PrintStream.println : (Ljava/lang/String;)V>  
16 getstatic #26 <java/lang/System.out : Ljava/io/PrintStream;>  
19 aload_1
20 invokevirtual #37 <FooCorporation.getSalario : ()F>  
23 invokevirtual #28 <java/io/PrintStream.println : (F)V>  
26 return
```
### [0] LineNumberTable
- Generic info 
  - Attribute name index`46` `<LineNumberTable>`
  - Attribute length `18`

- Specific info
  - Line number table length `4`  

| Number | Start PC | Line Number |  
|--------|----------|-------------|  
|       0|         0|           39|  
|       1|         8|           40|  
|       2|        16|           41|  
|       3|        26|           42|  


</details><br>

</details><br>

## **Attributes**
<details> <summary>Show more</summary> <hr>

### [0] SourceFile
- Generic info 
  - Attribute name index`51` `<SourceFile>`
  - Attribute length `2`

- Specific info
  - Source file name index `52` `<FooCorporation.java>`

</details><br>

